tragedy/__init__.py
tragedy-0.0.1.dist-info/LICENSE
tragedy-0.0.1.dist-info/METADATA
tragedy-0.0.1.dist-info/WHEEL
tragedy-0.0.1.dist-info/top_level.txt
tragedy-0.0.1.dist-info/RECORD
